[
  {
    "exp_id": "A1.1",
    "seed": 42,
    "config": {
      "alpha": 0.6,
      "w": null,
      "cap": 10,
      "k": 50,
      "tau": null,
      "lambda": null,
      "max_steps": 40,
      "max_handoffs": 2,
      "max_new_tokens": 768,
      "id": "A1.1",
      "soft_mode": "deterministic"
    },
    "n_samples": 5,
    "n_valid": 3,
    "n_timeouts": 0,
    "n_errors": 0,
    "accuracy": 0.0,
    "timeout_rate": 0.0,
    "error_rate": 0.0,
    "avg_wall_time_s": 21.274010181427002,
    "std_wall_time_s": 3.5687473348413183,
    "p50_wall_time_s": 18.949899673461914,
    "p90_wall_time_s": 24.84266929626465,
    "total_wall_time_s": 103.91794753074646,
    "samples_per_sec": 0.04811488408699217,
    "steps_per_sec": 0.07698381453918747,
    "avg_total_steps": 2.6666666666666665,
    "avg_latent_steps": 2.6666666666666665,
    "avg_explicit_tokens": 0.0,
    "avg_switches": 0.0,
    "std_switches": 0.0,
    "avg_top_k_mass": 1.0,
    "avg_peak_mem_gb": 3.5774441813333335,
    "max_peak_mem_gb": 3.752315392,
    "avg_bridge_rate": 0.0,
    "avg_bytes_per_step": 400.0,
    "avg_bytes_total": 1066.6666666666667,
    "timestamp": "2025-12-24T23:25:44.083248"
  }
]